Common_functions/__init__.py
PYPI_PUBLISHING-0.0.0.1.dist-info/LICENSE
PYPI_PUBLISHING-0.0.0.1.dist-info/METADATA
PYPI_PUBLISHING-0.0.0.1.dist-info/WHEEL
PYPI_PUBLISHING-0.0.0.1.dist-info/top_level.txt
PYPI_PUBLISHING-0.0.0.1.dist-info/RECORD
