Metadata-Version: 2.1
Name: PYPI-PUBLISHING
Version: 0.0.0.1
Summary: Experiment For publishing
Author: Abhishek
License-File: LICENSE
